{"i":0,"ts":1716215340000,"direction":"in","session_id":"infra-recovery-session-1","frame":{"id":"f1","v":"0.1","type":"hello","ts":"2024-05-20T14:29:00.000Z","payload":{"agent":"LTP-Infra-Node","version":"0.1","mode":"infrastructure"}},"prev_hash":"0000000000000000000000000000000000000000000000000000000000000000","signature":"simulated_sig_0","key_id":"infra-key-1","alg":"ed25519","hash":"f9bb7d5ea08f770d9efed1b933036ccbee19190f41ba5a02b50eef9186e4d1a5"}
{"i":1,"ts":1716215341000,"direction":"out","session_id":"infra-recovery-session-1","frame":{"id":"f2","v":"0.1","type":"orientation","ts":"2024-05-20T14:29:01.000Z","identity":"infra:node-1","payload":{"state":"STABLE","drift_level":"low","focus_momentum":1,"resources":{"db":"connected","latency":20}}},"prev_hash":"f9bb7d5ea08f770d9efed1b933036ccbee19190f41ba5a02b50eef9186e4d1a5","signature":"simulated_sig_1","key_id":"infra-key-1","alg":"ed25519","hash":"0590bb363371c4317e41079acb8faab22156cf3c70f549a34a523b71d7afe724"}
{"i":2,"ts":1716215345000,"direction":"in","session_id":"infra-recovery-session-1","frame":{"id":"f3","v":"0.1","type":"route_request","ts":"2024-05-20T14:29:05.000Z","payload":{"action":"place_order","id":"req-100","amount":50}},"prev_hash":"0590bb363371c4317e41079acb8faab22156cf3c70f549a34a523b71d7afe724","signature":"simulated_sig_2","key_id":"infra-key-1","alg":"ed25519","hash":"17a40809aedc261f54851b6047b9aeb8e8ce0ebf98dcd5e72c346d44ac51d559"}
{"i":3,"ts":1716215346000,"direction":"out","session_id":"infra-recovery-session-1","frame":{"id":"f4","v":"0.1","type":"route_response","ts":"2024-05-20T14:29:06.000Z","payload":{"admissible":true,"decision":"EXECUTE","reason":"OK","branches":[{"id":"primary","confidence":1,"status":"admissible","path":"db_write"}]}},"prev_hash":"17a40809aedc261f54851b6047b9aeb8e8ce0ebf98dcd5e72c346d44ac51d559","signature":"simulated_sig_3","key_id":"infra-key-1","alg":"ed25519","hash":"c09147d1ff370a754387fd81d99c946c185ab3fcdf166d42d8607c988d1754f7"}
{"i":4,"ts":1716215405000,"direction":"out","session_id":"infra-recovery-session-1","frame":{"id":"f5","v":"0.1","type":"orientation","ts":"2024-05-20T14:30:05.000Z","payload":{"state":"UNSTABLE","drift_level":"high","reason":"DB Connection Timeout","resources":{"db":"disconnected","latency":5000}}},"prev_hash":"c09147d1ff370a754387fd81d99c946c185ab3fcdf166d42d8607c988d1754f7","signature":"simulated_sig_4","key_id":"infra-key-1","alg":"ed25519","hash":"d53021019f1ec61f3a274428c391a3e3ec7a5c2aa2a38a6a8df46f133a3c7bdc"}
{"i":5,"ts":1716215410000,"direction":"in","session_id":"infra-recovery-session-1","frame":{"id":"f6","v":"0.1","type":"route_request","ts":"2024-05-20T14:30:10.000Z","payload":{"action":"place_order","id":"req-101","amount":120}},"prev_hash":"d53021019f1ec61f3a274428c391a3e3ec7a5c2aa2a38a6a8df46f133a3c7bdc","signature":"simulated_sig_5","key_id":"infra-key-1","alg":"ed25519","hash":"005d22633f1052dbf318f6adfba872e0d1f82312fe9988a426df05b1717096ff"}
{"i":6,"ts":1716215411000,"direction":"out","session_id":"infra-recovery-session-1","frame":{"id":"f7","v":"0.1","type":"route_response","ts":"2024-05-20T14:30:11.000Z","payload":{"admissible":false,"decision":"DEFER","reason":"SYSTEM_UNSTABLE","retry_condition":"state == STABLE","branches":[{"id":"deferred","confidence":1,"status":"deferred","reason":"Infrastructure unstable"}]}},"prev_hash":"005d22633f1052dbf318f6adfba872e0d1f82312fe9988a426df05b1717096ff","signature":"simulated_sig_6","key_id":"infra-key-1","alg":"ed25519","hash":"29b576a1f62052c4b22cdccfb2ca1fdde238016f05f33010975085d187c6fc35"}
{"i":7,"ts":1716215460000,"direction":"out","session_id":"infra-recovery-session-1","frame":{"id":"f8","v":"0.1","type":"orientation","ts":"2024-05-20T14:31:00.000Z","payload":{"state":"RECOVERING","drift_level":"medium","reason":"DB Connection Restored","resources":{"db":"reconnecting","latency":100}}},"prev_hash":"29b576a1f62052c4b22cdccfb2ca1fdde238016f05f33010975085d187c6fc35","signature":"simulated_sig_7","key_id":"infra-key-1","alg":"ed25519","hash":"8505e61050468416165f82ac9082265f4ffab9f79e744832e4cf74fddee77757"}
{"i":8,"ts":1716215465000,"direction":"in","session_id":"infra-recovery-session-1","frame":{"id":"f9","v":"0.1","type":"route_request","ts":"2024-05-20T14:31:05.000Z","payload":{"action":"place_order","id":"req-101","amount":120,"replay_context":{"original_frame_id":"f6","deferred_reason":"SYSTEM_UNSTABLE"}}},"prev_hash":"8505e61050468416165f82ac9082265f4ffab9f79e744832e4cf74fddee77757","signature":"simulated_sig_8","key_id":"infra-key-1","alg":"ed25519","hash":"906b3a070b144849b71cf05f0cee11e6eeaf905d9a779ab6783a68b233231275"}
{"i":9,"ts":1716215466000,"direction":"out","session_id":"infra-recovery-session-1","frame":{"id":"f10","v":"0.1","type":"route_response","ts":"2024-05-20T14:31:06.000Z","payload":{"admissible":true,"decision":"EXECUTE","reason":"RECOVERY_CONFIRMED","branches":[{"id":"primary","confidence":1,"status":"admissible","path":"db_write_replay"}]}},"prev_hash":"906b3a070b144849b71cf05f0cee11e6eeaf905d9a779ab6783a68b233231275","signature":"simulated_sig_9","key_id":"infra-key-1","alg":"ed25519","hash":"b968a04351d5c0fa42df4870f9550a6c96d0aaf8c0b5bae9d058c66695e235b1"}
{"i":10,"ts":1716215520000,"direction":"out","session_id":"infra-recovery-session-1","frame":{"id":"f11","v":"0.1","type":"orientation","ts":"2024-05-20T14:32:00.000Z","payload":{"state":"STABLE","drift_level":"low","resources":{"db":"connected","latency":15}}},"prev_hash":"b968a04351d5c0fa42df4870f9550a6c96d0aaf8c0b5bae9d058c66695e235b1","signature":"simulated_sig_10","key_id":"infra-key-1","alg":"ed25519","hash":"21d58289ceadce8848440f806188b0c13657429093d16c569378f8c731f1b746"}
{"i":11,"ts":1716215521000,"direction":"out","session_id":"infra-recovery-session-1","frame":{"id":"f12","v":"0.1","type":"focus_snapshot","ts":"2024-05-20T14:32:01.000Z","payload":{"drift":0.01,"note":"Recovery complete"}},"prev_hash":"21d58289ceadce8848440f806188b0c13657429093d16c569378f8c731f1b746","signature":"simulated_sig_11","key_id":"infra-key-1","alg":"ed25519","hash":"11bc404e536770c88f5824619442f6a7a021d206d535b81687dd083a7a92f071"}